reprep_tables.pyi
reprep.pyi
reprep_tables.cpython-310-x86_64-linux-gnu.so
reprep.cpython-310-x86_64-linux-gnu.so
reprep_z7-7.3.2201261049.dist-info/WHEEL
reprep_z7-7.3.2201261049.dist-info/top_level.txt
reprep_z7-7.3.2201261049.dist-info/RECORD
reprep_z7-7.3.2201261049.dist-info/METADATA
reprep_z7-7.3.2201261049.dist-info/zip-safe
reprep/static/jquery/jquery.js
reprep/static/jquery/jquery.ui.js
reprep/static/jquery/jquery.imageZoom.css
reprep/static/jquery/jquery.imageZoom.png
reprep/static/jquery/jquery.imageZoom.js
reprep/static/jquery/ui-lightness/jquery-ui-1.8.5.custom.css
reprep/static/jquery/ui-lightness/images/ui-bg_highlight-soft_100_eeeeee_1x100.png
reprep/static/jquery/ui-lightness/images/ui-bg_flat_10_000000_40x100.png
reprep/static/jquery/ui-lightness/images/ui-bg_diagonals-thick_20_666666_40x40.png
reprep/static/jquery/ui-lightness/images/ui-bg_glass_100_fdf5ce_1x400.png
reprep/static/jquery/ui-lightness/images/ui-bg_diagonals-thick_18_b81900_40x40.png
reprep/static/jquery/ui-lightness/images/ui-icons_ef8c08_256x240.png
reprep/static/jquery/ui-lightness/images/ui-icons_ffd27a_256x240.png
reprep/static/jquery/ui-lightness/images/ui-icons_ffffff_256x240.png
reprep/static/jquery/ui-lightness/images/ui-bg_glass_100_f6f6f6_1x400.png
reprep/static/jquery/ui-lightness/images/ui-bg_gloss-wave_35_f6a828_500x100.png
reprep/static/jquery/ui-lightness/images/ui-icons_222222_256x240.png
reprep/static/jquery/ui-lightness/images/ui-bg_highlight-soft_75_ffe45c_1x100.png
reprep/static/jquery/ui-lightness/images/ui-icons_228ef1_256x240.png
reprep/static/jquery/ui-lightness/images/ui-bg_glass_65_ffffff_1x400.png
reprep/static/jquery/tablesorter/build.xml
reprep/static/jquery/tablesorter/jquery.tablesorter.min.js
reprep/static/jquery/tablesorter/jquery.metadata.js
reprep/static/jquery/tablesorter/changelog
reprep/static/jquery/tablesorter/jquery.tablesorter.js
reprep/static/jquery/tablesorter/addons/pager/jquery.tablesorter.pager.css
reprep/static/jquery/tablesorter/addons/pager/jquery.tablesorter.pager.js
reprep/static/jquery/tablesorter/build/pack.js
reprep/static/jquery/tablesorter/build/min.js
reprep/static/jquery/tablesorter/build/js.jar
